osc_fish_complete/__init__.py
osc_fish_complete/complete.py
osc_fish_complete-0.0.1.dist-info/LICENSE
osc_fish_complete-0.0.1.dist-info/METADATA
osc_fish_complete-0.0.1.dist-info/WHEEL
osc_fish_complete-0.0.1.dist-info/entry_points.txt
osc_fish_complete-0.0.1.dist-info/top_level.txt
osc_fish_complete-0.0.1.dist-info/RECORD
