Metadata-Version: 2.1
Name: osc-fish-complete
Version: 0.0.1
Summary: opnestackclient command-line completion for fish shell
Home-page: https://github.com/buty4649/osc-fish-complete
Author: buty4649
Author-email: buty4649@gmail.com
License: MIT
Platform: UNKNOWN
